{
  "busiCode": null,
  "opId": null,
  "phone": null,
  "returnCode": "0",
  "returnMessage": null,
  "bean": {},
  "beans": [
    {
      "id": "000101",
      "name": "统一配置台",
      "value": "000101",
      "children": [
        {
          "id": "000101001",
          "name": "组织管理",
          "value": "000101001",
          "children": [
            {
              "id": "000101001001",
              "name": "组织机构维护",
              "value": "000101001001",
              "children": [
                {
                  "id": "000101001001001",
                  "name": "组织机构新增",
                  "value": "000101001001001"
                },
                {
                  "id": "000101001001002",
                  "name": "组织机构删除",
                  "value": "000101001001002"
                },
                {
                  "id": "000101001001003",
                  "name": "保存组织机构基本信息",
                  "value": "000101001001003"
                },
                {
                  "id": "000101001001004",
                  "name": "查询组织机构分配人员",
                  "value": "000101001001004"
                },
                {
                  "id": "000101001001005",
                  "name": "保存组织机构分配人员",
                  "value": "000101001001005"
                },
                {
                  "id": "000101001001006",
                  "name": "保存组织机构新建信息",
                  "value": "000101001001006"
                }
              ]
            },
            {
              "id": "000101001002",
              "name": "工作组维护",
              "value": "000101001002",
              "children": [
                {
                  "id": "000101001002001",
                  "name": "工作组新增",
                  "value": "000101001002001"
                },
                {
                  "id": "000101001002002",
                  "name": "工作组删除",
                  "value": "000101001002002"
                },
                {
                  "id": "000101001002003",
                  "name": "保存工作组信息修改",
                  "value": "000101001002003"
                },
                {
                  "id": "000101001002004",
                  "name": "保存工作组人员分配",
                  "value": "000101001002004"
                },
                {
                  "id": "000101001002005",
                  "name": "保存工作组责任人分配",
                  "value": "000101001002005"
                }
              ]
            }
          ]
        },
        {
          "id": "000101002",
          "name": "人员管理",
          "value": "000101002",
          "children": [
            {
              "id": "000101002001",
              "name": "人员信息维护",
              "value": "000101002001",
              "children": [
                {
                  "id": "000101002001001",
                  "name": "人员查询",
                  "value": "000101002001001"
                },
                {
                  "id": "000101002001002",
                  "name": "新增",
                  "value": "000101002001002"
                },
                {
                  "id": "000101002001003",
                  "name": "删除",
                  "value": "000101002001003"
                },
                {
                  "id": "000101002001004",
                  "name": "导入",
                  "value": "000101002001004"
                },
                {
                  "id": "000101002001005",
                  "name": "导出",
                  "value": "000101002001005"
                },
                {
                  "id": "000101002001006",
                  "name": "按条件导出",
                  "value": "000101002001006"
                },
                {
                  "id": "000101002001007",
                  "name": "更新全局缓存",
                  "value": "000101002001007"
                },
                {
                  "id": "000101002001008",
                  "name": "配置",
                  "value": "000101002001008"
                },
                {
                  "id": "000101002001009",
                  "name": "设置账号状态",
                  "value": "000101002001009"
                },
                {
                  "id": "000101002001010",
                  "name": "权限查看",
                  "value": "000101002001010"
                },
                {
                  "id": "000101002001011",
                  "name": "权限查询",
                  "value": "000101002001011"
                },
                {
                  "id": "000101002001012",
                  "name": "权限复制",
                  "value": "000101002001012"
                },
                {
                  "id": "000101002001013",
                  "name": "第三方账号",
                  "value": "000101002001013"
                },
                {
                  "id": "000101002001014",
                  "name": "打印",
                  "value": "000101002001014"
                },
                {
                  "id": "000101002001015",
                  "name": "配置数据权限",
                  "value": "000101002001015"
                },
                {
                  "id": "000101002001016",
                  "name": "导出人员权限",
                  "value": "000101002001016"
                },
                {
                  "id": "000101002001017",
                  "name": "导出人员角色",
                  "value": "000101002001017"
                },
                {
                  "id": "000101002001018001",
                  "name": "修改人员基本信息",
                  "value": "000101002001018001"
                },
                {
                  "id": "000101002001018002",
                  "name": "保存基本信息",
                  "value": "000101002001018002"
                },
                {
                  "id": "000101002001018003",
                  "name": "修改人员角色分配",
                  "value": "000101002001018003"
                },
                {
                  "id": "000101002001018004",
                  "name": "保存配置角色",
                  "value": "000101002001018004"
                },
                {
                  "id": "000101002001018005",
                  "name": "保存配置可赋角色",
                  "value": "000101002001018005"
                },
                {
                  "id": "000101002001018006",
                  "name": "修改人员权限配置",
                  "value": "000101002001018006"
                },
                {
                  "id": "000101002001018007",
                  "name": "保存配置功能权限",
                  "value": "000101002001018007"
                },
                {
                  "id": "000101002001018008",
                  "name": "保存配置数据权限",
                  "value": "000101002001018008"
                },
                {
                  "id": "000101002001018009",
                  "name": "保存配置可赋功能权限",
                  "value": "000101002001018009"
                },
                {
                  "id": "000101002001018010",
                  "name": "保存配置可赋数据权限",
                  "value": "000101002001018010"
                },
                {
                  "id": "000101002001018012",
                  "name": "查看工作组配置",
                  "value": "000101002001018012"
                },
                {
                  "id": "000101002001018013",
                  "name": "保存工作组配置",
                  "value": "000101002001018013"
                },
                {
                  "id": "000101002001018014",
                  "name": "修改人员平台工号配置",
                  "value": "000101002001018014"
                },
                {
                  "id": "000101002001018015",
                  "name": "平台工号新增",
                  "value": "000101002001018015"
                },
                {
                  "id": "000101002001018016",
                  "name": "平台工号删除",
                  "value": "000101002001018016"
                }
              ]
            },
            {
              "id": "000101002002",
              "name": "人员权限查询",
              "value": "000101002002"
            }
          ]
        },
        {
          "id": "000101003",
          "name": "权限管理",
          "value": "000101003",
          "children": [
            {
              "id": "000101003001",
              "name": "功能权限维护",
              "value": "000101003001",
              "children": [
                {
                  "id": "000101003001001",
                  "name": "保存功能权限人员分配",
                  "value": "000101003001001"
                },
                {
                  "id": "000101003001002",
                  "name": "保存功能权限角色分配",
                  "value": "000101003001002"
                }
              ]
            },
            {
              "id": "000101003002",
              "name": "角色维护",
              "value": "000101003002",
              "children": [
                {
                  "id": "000101003002001",
                  "name": "新增角色",
                  "value": "000101003002001"
                },
                {
                  "id": "000101003002002",
                  "name": "删除角色",
                  "value": "000101003002002"
                },
                {
                  "id": "000101003002003",
                  "name": "保存基本信息",
                  "value": "000101003002003"
                },
                {
                  "id": "000101003002004",
                  "name": "保存人员分配",
                  "value": "000101003002004"
                },
                {
                  "id": "000101003002005",
                  "name": "保存权限配置",
                  "value": "000101003002005"
                },
                {
                  "id": "000101003002006",
                  "name": "保存可赋人员分配",
                  "value": "000101003002006"
                },
                {
                  "id": "000101003002007",
                  "name": "保存功能权限",
                  "value": "000101003002007"
                },
                {
                  "id": "000101003002008",
                  "name": "保存数据权限",
                  "value": "000101003002008"
                }
              ]
            },
            {
              "id": "000101003003",
              "name": "人员权限维护",
              "value": "000101003003"
            },
            {
              "id": "000101003004",
              "name": "数据权限维护",
              "value": "000101003004",
              "children": [
                {
                  "id": "000101003004003",
                  "name": "保存数据权限人员分配",
                  "value": "000101003004003"
                },
                {
                  "id": "000101003004004",
                  "name": "保存数据权限角色分配",
                  "value": "000101003004004"
                }
              ]
            }
          ]
        },
        {
          "id": "000101004",
          "name": "业务日志管理",
          "value": "000101004",
          "children": [
            {
              "id": "000101004001",
              "name": "登录日志查询",
              "value": "000101004001",
              "children": [
                {
                  "id": "000101004001001",
                  "name": "查询登录日志",
                  "value": "000101004001001"
                }
              ]
            },
            {
              "id": "000101004002",
              "name": "业务日志查询",
              "value": "000101004002",
              "children": [
                {
                  "id": "000101004002001",
                  "name": "查询业务日志",
                  "value": "000101004002001"
                }
              ]
            },
            {
              "id": "000101004003",
              "name": "用户访问服务器日志查询",
              "value": "000101004003"
            },
            {
              "id": "000101004004",
              "name": "在线用户列表",
              "value": "000101004004"
            }
          ]
        },
        {
          "id": "000101005",
          "name": "系统维护",
          "value": "000101005",
          "children": [
            {
              "id": "000101005001",
              "name": "菜单项维护",
              "value": "000101005001"
            },
            {
              "id": "000101005002",
              "name": "系统参数维护",
              "value": "000101005002",
              "children": [
                {
                  "id": "000101005002001",
                  "name": "修改系统参数",
                  "value": "000101005002001"
                }
              ]
            },
            {
              "id": "000101005003",
              "name": "数据字典维护",
              "value": "000101005003",
              "children": [
                {
                  "id": "000101005003001",
                  "name": "数据字典查询",
                  "value": "000101005003001"
                },
                {
                  "id": "000101005003002",
                  "name": "数据字典新增",
                  "value": "000101005003002"
                },
                {
                  "id": "000101005003003",
                  "name": "数据字典删除",
                  "value": "000101005003003"
                },
                {
                  "id": "000101005003004001",
                  "name": "静态数据字典新增",
                  "value": "000101005003004001"
                },
                {
                  "id": "000101005003004002",
                  "name": "静态数据字典删除",
                  "value": "000101005003004002"
                }
              ]
            },
            {
              "id": "000101005004",
              "name": "更新全局缓存",
              "value": "000101005004"
            }
          ]
        },
        {
          "id": "000101006",
          "name": "平台维护",
          "value": "000101006",
          "children": [
            {
              "id": "000101006001",
              "name": "CTI资源管理",
              "value": "000101006001"
            },
            {
              "id": "000101006003",
              "name": "技能队列关联地市管理",
              "value": "000101006003"
            }
          ]
        }
      ]
    }
  ],
  "object": null
}